pobm/_ErrorHandler.py
pobm/_ResultsClasses.py
pobm/__init__.py
pobm/prep.py
pobm/obm/__init__.py
pobm/obm/burden.py
pobm/obm/complex.py
pobm/obm/desat.py
pobm/obm/general.py
pobm/obm/periodicity.py
pobm-1.2.0.dist-info/AUTHORS.rst
pobm-1.2.0.dist-info/LICENSE.txt
pobm-1.2.0.dist-info/METADATA
pobm-1.2.0.dist-info/WHEEL
pobm-1.2.0.dist-info/top_level.txt
pobm-1.2.0.dist-info/RECORD
