Metadata-Version: 2.1
Name: pobm
Version: 1.2.0
Summary: Oximetry Toolbox, for extracting biomarkers from spo2 signal
Home-page: http://aim-lab.github.io
Author: "Jeremy Levy"
Author-email: "jeremy.levy@campus.technion.ac.il"
License: proprietary
Project-URL: Documentation, http://aim-lab.github.io
Platform: any
Classifier: Development Status :: 4 - Beta
Classifier: Programming Language :: Python
License-File: LICENSE.txt
License-File: AUTHORS.rst
Requires-Dist: numpy
Requires-Dist: scipy
Requires-Dist: lempel-ziv-complexity
Provides-Extra: testing
Requires-Dist: pytest ; extra == 'testing'
Requires-Dist: pytest-cov ; extra == 'testing'
